LICENSE
MANIFEST.in
README.md
setup.py
git_file_keyword/__init__.py
git_file_keyword/config.py
git_file_keyword/exception.py
git_file_keyword/extractor.py
git_file_keyword/plugin.py
git_file_keyword/plugin_llm.py
git_file_keyword/result.py
git_file_keyword/stopword.py
git_file_keyword/utils.py
git_file_keyword.egg-info/PKG-INFO
git_file_keyword.egg-info/SOURCES.txt
git_file_keyword.egg-info/dependency_links.txt
git_file_keyword.egg-info/entry_points.txt
git_file_keyword.egg-info/requires.txt
git_file_keyword.egg-info/top_level.txt
git_file_keyword/cli/__init__.py
git_file_keyword/data/stopword-iso.txt