Metadata-Version: 2.1
Name: git-file-keyword
Version: 0.2.3
Summary: Extract keywords of your code files
Home-page: https://github.com/williamfzc/git-file-keyword
Author: williamfzc
Author-email: williamfzc@foxmail.com
License: Apache-2.0
Platform: UNKNOWN
Classifier: License :: OSI Approved :: Apache Software License
Classifier: Programming Language :: Python
Classifier: Programming Language :: Python :: 3
License-File: LICENSE
